README.txt
setup.py
dsync/__init__.py
dsync/builder.py
dsync/generator.py
dsync/synchor.py
dsync/typeinfo.py
dsync.egg-info/PKG-INFO
dsync.egg-info/SOURCES.txt
dsync.egg-info/dependency_links.txt
dsync.egg-info/top_level.txt
dsync.egg-info/zip-safe
test/test_sysconfig.py